pubid2bib/__init__.py
pubid2bib/pubid2bib.py
pubid2bib-0.0.1.dist-info/LICENSE
pubid2bib-0.0.1.dist-info/METADATA
pubid2bib-0.0.1.dist-info/WHEEL
pubid2bib-0.0.1.dist-info/entry_points.txt
pubid2bib-0.0.1.dist-info/top_level.txt
pubid2bib-0.0.1.dist-info/RECORD
