Metadata-Version: 2.1
Name: pubid2bib
Version: 0.0.1
Summary: Command line tool to create BibTeX bibliographic entries for given publication identifiers 
Author-email: Andrés Becerra Sandoval <andres.becerra@gmail.com>
Project-URL: Homepage, https://github.com/abecerra/pubid2bib
Project-URL: Issues, https://github.com/abecerra/pubid2bib/issues
Classifier: Programming Language :: Python :: 3
Classifier: License :: OSI Approved :: MIT License
Classifier: Operating System :: OS Independent
Requires-Python: >=3.8
License-File: LICENSE
